snapmap_archiver/__init__.py
snapmap_archiver/__main__.py
snapmap_archiver/coordinates.py
snapmap_archiver/snap.py
snapmap_archiver/SnapmapArchiver.py
snapmap_archiver/time.py
snapmap_archiver-2.4.1.dist-info/entry_points.txt
snapmap_archiver-2.4.1.dist-info/LICENSE
snapmap_archiver-2.4.1.dist-info/METADATA
snapmap_archiver-2.4.1.dist-info/WHEEL
snapmap_archiver-2.4.1.dist-info/RECORD
