Metadata-Version: 2.1
Name: snapmap-archiver
Version: 2.4.1
Summary: Download all Snap Map content from a specific location.
License: GPL-3.0-or-later
Author: Miles Greenwark
Author-email: Millez.Dev@gmail.com
Requires-Python: >=3.10,<4.0
Classifier: License :: OSI Approved :: GNU General Public License v3 or later (GPLv3+)
Classifier: Programming Language :: Python :: 3
Classifier: Programming Language :: Python :: 3.10
Classifier: Programming Language :: Python :: 3.11
Classifier: Programming Language :: Python :: 3.12
Requires-Dist: aiofiles (>=23.2.1,<24.0.0)
Requires-Dist: alive-progress (>=3.1.5,<4.0.0)
Requires-Dist: httpx (>=0.27.0,<0.28.0)
Requires-Dist: loguru (>=0.7.2,<0.8.0)
Requires-Dist: requests (>=2.25.1,<3.0.0)
